halcyon/__init__.py
halcyon/config.py
halcyon/console.py
halcyon/infer/__init__.py
halcyon/infer/download.py
halcyon/infer/infer.py
halcyon/infer/inferer.py
halcyon/ml/.gitignore
halcyon/ml/__init__.py
halcyon/ml/net/__init__.py
halcyon/ml/net/base.py
halcyon/ml/net/cnn.py
halcyon/ml/net/decoder/__init__.py
halcyon/ml/net/decoder/decoder.py
halcyon/ml/net/decoder/helper.py
halcyon/ml/net/decoder/inference_decoder.py
halcyon/ml/net/decoder/train_decoder.py
halcyon/ml/net/encoder.py
halcyon/ml/net/hp_params.py
halcyon/ml/net/net_inference.py
halcyon/ml/net/net_train.py
halcyon/ml/net/saver.py
halcyon/ml/net/sub_net.py
halcyon/models/__init__.py
halcyon/models/fast5.py
halcyon/models/seq.py
pyhalcyon-0.1.1.dist-info/entry_points.txt
pyhalcyon-0.1.1.dist-info/LICENSE
pyhalcyon-0.1.1.dist-info/WHEEL
pyhalcyon-0.1.1.dist-info/METADATA
pyhalcyon-0.1.1.dist-info/RECORD
