Metadata-Version: 2.1
Name: pyhalcyon
Version: 0.1.1
Summary: 
Author: Hiroki Konishi
Author-email: relastle@gmail.com
Requires-Python: ==3.7.4
Classifier: Programming Language :: Python :: 3
Requires-Dist: biopython (==1.75)
Requires-Dist: click (==7.1.2)
Requires-Dist: click-help-colors (==0.8)
Requires-Dist: h5py (==2.10.0)
Requires-Dist: logzero (==1.5.0)
Requires-Dist: more-itertools (==8.4.0)
Requires-Dist: numpy (<1.17)
Requires-Dist: requests (==2.24.0)
Requires-Dist: tensorflow (<1.15.0)
Requires-Dist: ujson (==1.35)
